{"sections":{"main":{"type":"main-page","disabled":true,"settings":{}},"slideshow_split_nLgbaK":{"type":"slideshow-split","blocks":{"slide_aHciLh":{"type":"slide","settings":{"top_subheading":"Apr28 - May12","title":"Mother's Day Sale","title_size":60,"subheading":"Tailored for longer text and smaller images. Explain more about your promotion.","link":"","link_text":"Shop Now","link_2":"","link_text_2":"","text_position":"left","image":"shopify:\/\/shop_images\/kitchen_2e6149e7-b95b-4c11-9274-acdf5d19de46.png","indent_image":false,"color_scheme":"2"}}},"block_order":["slide_aHciLh"],"disabled":true,"name":"t:labels.split_optional_slides","settings":{"full_width":true,"height":650,"height_mobile":450,"style":"arrows","autoplay":true,"autoplay_speed":7}},"slideshow_UQbxaL":{"type":"slideshow","blocks":{"hero_z6tHbU":{"type":"hero","settings":{"top_subheading":"","title":"","title_size":59,"subheading":"","link":"","link_text":"","link_2":"","link_text_2":"","color_accent":"#dc6682","text_align":"vertical-bottom horizontal-left","image":"shopify:\/\/shop_images\/banner1_no.jpg","overlay_opacity":0}}},"block_order":["hero_z6tHbU"],"name":"t:labels.hero_optional_slides","settings":{"full_width":true,"desktop_size":0,"mobile_size":0,"style":"arrows","autoplay":true,"autoplay_speed":7}},"page_navigation_RJnNdr":{"type":"page-navigation","blocks":{"nav_item_XAn6t6":{"type":"nav_item","settings":{"nav_text":"Partial Sun","section_id":"partial-sun","is_active":true}},"nav_item_E63jmh":{"type":"nav_item","settings":{"nav_text":"Full Sun","section_id":"full-sun","is_active":false}},"nav_item_kLrnGd":{"type":"nav_item","settings":{"nav_text":"Outdoor TV Cabinet","section_id":"tv-cabinet","is_active":false}},"nav_item_JjcNYT":{"type":"nav_item","settings":{"nav_text":"Lifestyle TVs","section_id":"lifestyle-tvs","is_active":false}}},"block_order":["nav_item_XAn6t6","nav_item_E63jmh","nav_item_kLrnGd","nav_item_JjcNYT"],"name":"Page Navigation","settings":{"nav_bg_color":"#e24155","nav_border_color":"#eeeeee","active_bg_color":"rgba(0,0,0,0)","active_text_color":"#ffffff","inactive_text_color":"#1c5544","sticky_nav":true}},"product_category_UamWPD":{"type":"product-category","name":"Product Category","settings":{"section_id":"section1","main_heading_1":"","heading":"Happy stage at the kitchen counter, with laughterfilling the air.","main_heading_2":"","heading_color_1":"#e24155","subheading":"","description":"","bg_color":"#ffedeb","discount_bg_color":"#e24155","discount_color":"#ffffff","discount_size":15,"price_color":"#e24155","button_bg_color":"#e24155","button_text_color":"#ffffff","products":["under-counter-tv","sylvox-15-6-smart-under-cabinet-kitchen-tv-silver","sylvox-15-6-smart-under-cabinet-tv-for-kitchen","sylvox-15-6-smart-under-cabinet-kitchen-tv-black-new-arrival","sylvox-15-6-smart-under-cabinet-tv-for-kitchen-1"]}},"product_category_NmCCd9":{"type":"product-category","name":"Product Category","settings":{"section_id":"section1","main_heading_1":"","heading":"More than a reflection — It's her moment to glow.","main_heading_2":"","heading_color_1":"#e24155","subheading":"","description":"","bg_color":"#ffedeb","discount_bg_color":"#e24155","discount_color":"#ffffff","discount_size":15,"price_color":"#e24155","button_bg_color":"#e24155","button_text_color":"#ffffff","products":["19-waterproof-smart-magic-mirror-tv-for-bathroomon-wall-model","24inch-waterproof-mirror-tv-for-bathroom-1","24inch-waterproof-mirror-tv-for-bathroom","32-smart-waterproof-mirror-tv-for-bathroom","32inch-waterproof-mirror-tv-for-bathroom"]}},"pagefly_section_HKFbQW":{"type":"pagefly-section","name":"PageFly Section","settings":{"section_id":"pf-862716de"}},"newsletter_new_yDV6U7":{"type":"newsletter-new","name":"Newsletter Subscription","settings":{"section_id":"section1","heading_line1_1":"","heading_line1":"Worried You'll Miss the Deal?","heading_line1_2":"","heading_color_1_desktop":"#e24155","description":"Be the First to Know!","input_placeholder":"Subscribe to win your gift for free!","button_text":"Subscribe Now","terms_text":"I agree to the Terms of Service and Privacy Policy.","terms_url":"","max_width":900,"section_height":500,"background_color":"rgba(0,0,0,0)","background_image":"shopify:\/\/shop_images\/2024050711.png","form_bg_color":"#ffffff","heading_size_desktop_1":48,"heading_size_desktop_2":48,"heading_color_2_desktop":"#e24155","description_size_desktop":16,"description_color_desktop":"#777777","heading_size_mobile_1":32,"heading_size_mobile_2":32,"heading_color_1_mobile":"#2e7d5f","heading_color_2_mobile":"#e24155","description_size_mobile":14,"description_color_mobile":"#777777","input_bg_color":"#f5f5f5","input_text_color":"#333333","button_bg_color":"#e24155","button_text_color":"#ffffff"}},"advantages_UPfqnh":{"type":"advantages","blocks":{"feature_pyJbri":{"type":"feature","settings":{"icon":"shopify:\/\/shop_images\/png__1_120_9b3ca34c-148f-421a-9645-a19f2485e54e.png","title":"30 Days Money-back Guarantee","text":""}},"feature_mQ8bpJ":{"type":"feature","settings":{"icon":"shopify:\/\/shop_images\/png__1_88.png","title":"1 Year Warranty","text":""}},"feature_Bpejd8":{"type":"feature","settings":{"icon":"shopify:\/\/shop_images\/In_Transit_989213c9-b5dc-4ccc-b7ec-864e815b5182.svg","title":"2-5 days Delivery","text":""}},"feature_bNhr8L":{"type":"feature","settings":{"icon":"shopify:\/\/shop_images\/Hotline_47ed6e07-be9a-48c1-91f7-02ba1e94c827.svg","title":"Lifetime Customer Support","text":""}}},"block_order":["feature_pyJbri","feature_mQ8bpJ","feature_Bpejd8","feature_bNhr8L"],"name":"Advantages Showcase","settings":{"section_id":"section1","heading_line1_1":"","heading_line1":"Loved by our exclusive advantages","heading_line1_2":"","heading_color_1_desktop":"#e24155","description":"","max_width":900,"background_color":"#ffedeb","heading_size_desktop_1":48,"heading_size_desktop_2":48,"heading_color_2_desktop":"#b06a8a","description_size_desktop":16,"description_color_desktop":"#777777","feature_title_size_desktop":18,"feature_title_color_desktop":"#333333","feature_text_size_desktop":16,"feature_text_color_desktop":"#666666","heading_size_mobile_1":32,"heading_size_mobile_2":32,"description_size_mobile":14,"description_color_mobile":"#777777","feature_title_size_mobile":16,"feature_title_color_mobile":"#333333","feature_text_size_mobile":14,"feature_text_color_mobile":"#666666"}},"awards_showcase_XLejzn":{"type":"awards-showcase","blocks":{"award_row_kHLRHm":{"type":"award_row","settings":{"award1_image":"shopify:\/\/shop_images\/1_cfd8fdb8-2696-43eb-8d52-001c247a9e83.png","award1_link":"","award1_title":"","award2_image":"shopify:\/\/shop_images\/2_0a6000a6-8f1d-49f4-9bc4-7ea51fd15254.png","award2_link":"","award2_title":"","award3_image":"shopify:\/\/shop_images\/2_811f1aa0-3716-49b9-9a04-c7281ed29d66.png","award3_link":"","award3_title":"","award4_image":"shopify:\/\/shop_images\/3_369549f0-516e-4b0a-8969-4b44f49c7d3d.png","award4_link":"","award4_title":""}},"award_row_E9WrTz":{"type":"award_row","settings":{"award1_image":"shopify:\/\/shop_images\/4_bb65c4e0-113e-4b0e-a54e-b4bb6171b934.png","award1_link":"","award1_title":"","award2_image":"shopify:\/\/shop_images\/5_636c2e00-983b-4683-99ed-cbbc7462ed76.png","award2_link":"","award2_title":"","award3_image":"shopify:\/\/shop_images\/6_56bf34a7-fab3-4bdd-a3c3-17a6ca26dcb8.png","award3_link":"","award3_title":"","award4_image":"shopify:\/\/shop_images\/7_fb4026a5-49ce-4e21-ad03-b3781156f5b1.png","award4_link":"","award4_title":""}}},"block_order":["award_row_kHLRHm","award_row_E9WrTz"],"name":"Awards Showcase","settings":{"section_id":"section1","heading_line1_1":"","heading_line1":"Awards and Honours","heading_line1_2":"","heading_color_1_desktop":"#e24155","description":"Sylvox has deepened its competencies in various fields,\nearning the recognition of users and professional institutions all over the world.","max_width":900,"background_color":"#ffedeb","heading_size_desktop_1":48,"heading_size_desktop_2":48,"description_size_desktop":16,"description_color_desktop":"#777777","heading_size_mobile_1":32,"description_size_mobile":14,"description_color_mobile":"#777777"}},"text_columns_VG9khg":{"type":"text-columns","blocks":{"text_block_UkQ6q6":{"type":"text_block","settings":{"enable_image":true,"image_mask":"none","image_width":650,"title":"Waterproof Outdoor TV Cover","text":"<p>Spend Over $119<br\/><\/p>","button_label":"Click to View Rules","button_link":""}},"text_block_MXR4bJ":{"type":"text_block","settings":{"enable_image":true,"image_mask":"none","image_width":650,"title":"Sylvox S2 Soundbar","text":"<p>Spend Over $699<\/p>","button_label":"Click to View Rules","button_link":""}}},"block_order":["text_block_UkQ6q6","text_block_MXR4bJ"],"disabled":true,"name":"t:labels.text_columns_with","settings":{"title":"Sylvox Lifestyle Gifts","align_text":"center","divider":false,"color_scheme":"none"}},"background_image_text_P47xkL":{"type":"background-image-text","disabled":true,"name":"t:labels.large_image_with","settings":{"subtitle":"","title":"","text":"","button_label":"","button_link":"","image":"shopify:\/\/shop_images\/Kitchen.png","layout":"left","height":650,"parallax":false,"parallax_direction":"top"}},"image_compare_tFY8iw":{"type":"image-compare","blocks":{"image_aaWEtM":{"type":"image","settings":{"image":"shopify:\/\/shop_images\/Kitchen.png"}},"image_67br37":{"type":"image","settings":{"image":"shopify:\/\/shop_images\/Bathroom.jpg"}}},"block_order":["image_aaWEtM","image_67br37"],"disabled":true,"name":"t:labels.image_comparison","settings":{"heading":"","heading_size":"h2","heading_position":"center","fullwidth":true,"slider_style":"classic","height":670,"color":"#ffffff"}},"category_tabs_8QxtJX":{"type":"category-tabs","blocks":{"category_BAGUjW":{"type":"category","settings":{"category_name":"Kitchen TV","collection":"kitchen-tv-mothers-day","products_to_show":3,"is_active":true}},"category_dNQGhP":{"type":"category","settings":{"category_name":"Bathroom TV","collection":"mirror-tv","products_to_show":3,"is_active":false}}},"block_order":["category_BAGUjW","category_dNQGhP"],"disabled":true,"name":"Category Product tabs","settings":{"section_id":"section1","heading_line1_1":"","heading_line1":"Celebrate For","heading_line1_2":"","heading_line2":"Every ''MOMent''","heading_line3":"","description":"Anytime, anywhere, stop busy and enjoy freedom for her","max_width":1200,"background_color":"#fff4f4","heading_size_desktop_1":48,"heading_size_desktop_2":48,"heading_size_desktop_3":48,"heading_color_1_desktop":"#D97D7D","heading_color_2_desktop":"#C56C86","heading_color_3_desktop":"#2E7D5F","description_size_desktop":16,"description_color_desktop":"#777777","heading_size_mobile_1":32,"heading_size_mobile_2":32,"heading_size_mobile_3":32,"description_size_mobile":14,"description_color_mobile":"#777777","discount_bg_color":"#dc6682","discount_color":"#ffffff","discount_size":15,"price_color":"#bc084c","button_bg_color":"#dc6682","button_text_color":"#ffffff"}},"background_image_text_J6g3Wd":{"type":"background-image-text","disabled":true,"name":"t:labels.large_image_with","settings":{"subtitle":"","title":"","text":"","button_label":"","button_link":"","image":"shopify:\/\/shop_images\/outdoor.jpg","layout":"left","height":650,"parallax":false,"parallax_direction":"top"}},"category_tabs_Qn3UFk":{"type":"category-tabs","blocks":{"category_NfNx9C":{"type":"category","settings":{"category_name":"Deck Pro 2.0","collection":"sylvox-deck-pro-2-0-outdoor-tv-spring-sale","products_to_show":4,"is_active":true}},"category_DDQdLV":{"type":"category","settings":{"category_name":"Deck Pro Qled 2.0","collection":"deck-pro-qled-2-0","products_to_show":3,"is_active":false}}},"block_order":["category_NfNx9C","category_DDQdLV"],"disabled":true,"name":"Category Product tabs","settings":{"section_id":"section1","heading_line1_1":"","heading_line1":"Bright Days","heading_line1_2":"","heading_line2":"Brighter Memories","heading_line3":"","description":"Shine Bright with Her Smile","max_width":1200,"background_color":"#fff4f4","heading_size_desktop_1":48,"heading_size_desktop_2":48,"heading_size_desktop_3":48,"heading_color_1_desktop":"#D97D7D","heading_color_2_desktop":"#C56C86","heading_color_3_desktop":"#2E7D5F","description_size_desktop":16,"description_color_desktop":"#777777","heading_size_mobile_1":32,"heading_size_mobile_2":32,"heading_size_mobile_3":32,"description_size_mobile":14,"description_color_mobile":"#777777","discount_bg_color":"#b06a8a","discount_color":"#ffffff","discount_size":15,"price_color":"#bc084c","button_bg_color":"#dc6682","button_text_color":"#ffffff"}},"rich_text_3fcXy6":{"type":"rich-text","blocks":{"heading_bDgHJz":{"type":"heading","settings":{"title":"Extra- Special Portable TV for Special Mom","heading_size":"h2"}},"text_dyDYWL":{"type":"text","disabled":true,"settings":{"enlarge_text":true,"text":""}}},"block_order":["heading_bDgHJz","text_dyDYWL"],"disabled":true,"name":"t:labels.rich_text","settings":{"align_text":"center","narrow_column":false,"color_scheme":"1","divider":true}},"featured_collections_CYGAF3":{"type":"featured-collections","blocks":{"collection_kwY6pp":{"type":"collection","settings":{"collection":"outdoor-tv","title":""}},"collection_mawbr7":{"type":"collection","settings":{"collection":"12v-rv-tv","title":""}},"collection_bwRwbH":{"type":"collection","settings":{"collection":"kitchen-tv","title":""}},"collection_AwCN46":{"type":"collection","settings":{"collection":"portable-tv","title":""}},"collection_pJNBA8":{"type":"collection","settings":{"collection":"mirror-tv","title":""}}},"block_order":["collection_kwY6pp","collection_mawbr7","collection_bwRwbH","collection_AwCN46","collection_pJNBA8"],"disabled":true,"settings":{"title":"More Popular categories","heading_size":"h2","heading_position":"center","divider":false}},"slideshow_split_RWFmFB":{"type":"slideshow-split","blocks":{"slide_QjzppK":{"type":"slide","settings":{"top_subheading":"Sylvox 15.6\" Waterproof Portable Battery Powered TV","title":"Sylvox 15.6\" Portable TV","title_size":40,"subheading":"Waterproof | Smart TV | Rechargeable battery","link":"","link_text":"Buy Now","link_2":"","link_text_2":"","text_position":"left","image":"shopify:\/\/shop_images\/kitchen_2e6149e7-b95b-4c11-9274-acdf5d19de46.png","indent_image":false,"color_scheme":"none"}}},"block_order":["slide_QjzppK"],"disabled":true,"name":"t:labels.split_optional_slides","settings":{"full_width":true,"height":450,"height_mobile":350,"style":"minimal","autoplay":true,"autoplay_speed":7}},"rich_text_hUzMkD":{"type":"rich-text","blocks":{"heading_QTHWPb":{"type":"heading","settings":{"title":"Mystery Box For Mom","heading_size":"h2"}},"text_VVNAwz":{"type":"text","settings":{"enlarge_text":true,"text":"<p>Apr28-May12<\/p>"}}},"block_order":["heading_QTHWPb","text_VVNAwz"],"disabled":true,"name":"t:labels.rich_text","settings":{"align_text":"center","narrow_column":true,"color_scheme":"1","divider":false}},"text_columns_P7YtBT":{"type":"text-columns","blocks":{"text_block_aa433C":{"type":"text_block","settings":{"enable_image":true,"image_mask":"none","image_width":60,"title":"Example title","text":"<p>Use this section to explain a set of product features, to link to a series of pages, or to answer common questions.<\/p>","button_label":"Optional button","button_link":""}},"text_block_NPnhkF":{"type":"text_block","settings":{"enable_image":true,"image_mask":"none","image_width":650,"title":"Example title","text":"<p>Use this section to explain a set of product features, to link to a series of pages, or to answer common questions.<\/p>","button_label":"Optional button","button_link":""}},"text_block_bHGLFC":{"type":"text_block","settings":{"enable_image":true,"image_mask":"none","image_width":650,"title":"Example title","text":"<p>Use this section to explain a set of product features, to link to a series of pages, or to answer common questions.<\/p>","button_label":"Optional button","button_link":""}}},"block_order":["text_block_aa433C","text_block_NPnhkF","text_block_bHGLFC"],"disabled":true,"name":"t:labels.text_columns_with","settings":{"title":"","align_text":"left","divider":false,"color_scheme":"none"}},"rich_text_KafLyU":{"type":"rich-text","blocks":{"heading_cgiBgD":{"type":"heading","settings":{"title":"Why Choose Us?","heading_size":"h2"}}},"block_order":["heading_cgiBgD"],"disabled":true,"settings":{"align_text":"center","narrow_column":true,"color_scheme":"none","divider":false}},"402eec52-ad84-4fb6-8a84-e6c26028d7b5":{"type":"text-with-icons","blocks":{"template--15324807168061__402eec52-ad84-4fb6-8a84-e6c26028d7b5-text_block-1":{"type":"text_block","settings":{"icon":"thumbs-up","title":"Free Delivery","text":""}},"text_block_NrXKVK":{"type":"text_block","settings":{"icon":"wallet","title":"30-Day Money-Back guarantee","text":""}},"template--15324807168061__402eec52-ad84-4fb6-8a84-e6c26028d7b5-text_block-2":{"type":"text_block","settings":{"icon":"sales-tag","title":"Hassle-free Warranty","text":""}},"template--15324807168061__402eec52-ad84-4fb6-8a84-e6c26028d7b5-text_block-3":{"type":"text_block","settings":{"icon":"globe","title":"Global Support","text":""}},"1c595375-8473-4c21-b086-6c4814788cfd":{"type":"text_block","settings":{"icon":"wallet","title":"Secure Payment","text":""}},"3d2c6f2b-405d-4157-922c-d49614c5c543":{"type":"text_block","settings":{"icon":"ribbon","title":"Robust Product Portfolio","text":""}}},"block_order":["template--15324807168061__402eec52-ad84-4fb6-8a84-e6c26028d7b5-text_block-1","text_block_NrXKVK","template--15324807168061__402eec52-ad84-4fb6-8a84-e6c26028d7b5-text_block-2","template--15324807168061__402eec52-ad84-4fb6-8a84-e6c26028d7b5-text_block-3","1c595375-8473-4c21-b086-6c4814788cfd","3d2c6f2b-405d-4157-922c-d49614c5c543"],"disabled":true,"settings":{"title":"","align_text":"center","desktop_columns_per_row":3,"icon_color":"#000000","button_label":"","button_link":"","divider":false}}},"order":["main","slideshow_split_nLgbaK","slideshow_UQbxaL","page_navigation_RJnNdr","product_category_UamWPD","product_category_NmCCd9","pagefly_section_HKFbQW","newsletter_new_yDV6U7","advantages_UPfqnh","awards_showcase_XLejzn","text_columns_VG9khg","background_image_text_P47xkL","image_compare_tFY8iw","category_tabs_8QxtJX","background_image_text_J6g3Wd","category_tabs_Qn3UFk","rich_text_3fcXy6","featured_collections_CYGAF3","slideshow_split_RWFmFB","rich_text_hUzMkD","text_columns_P7YtBT","rich_text_KafLyU","402eec52-ad84-4fb6-8a84-e6c26028d7b5"]}